[{"play_time":"3:17","thumbnail":"http://i.ytimg.com/vi/qaJg3b3mHbk/mqdefault.jpg","title":"9. Best Plays of The Week | League of Legends","video_date":"2015-11-02T17:26:03.706+09:00","view_ct":35,"id":"5637286b6e65773023000004"},{"play_time":"32:05","thumbnail":"http://i.ytimg.com/vi/-L1u2kREBPw/mqdefault.jpg","title":"SKT T1 Faker - Lulu vs Azir - OG Niels, EUW LOL Challenger","video_date":"2015-11-02T03:10:04.648+09:00","view_ct":4,"id":"5636b7ec6e6577298c00000b"},{"play_time":"34:04","thumbnail":"http://i.ytimg.com/vi/c2_OJ9hc2OI/mqdefault.jpg","title":"SKT T1 Faker - Kassadin Mid Lane - EUW SoloQ","video_date":"2015-11-01T23:10:04.104+09:00","view_ct":16,"id":"5636b7ec6e6577298c000007"},{"play_time":"14:57","thumbnail":"http://i.ytimg.com/vi/x7mxdbYSOwo/mqdefault.jpg","title":"166. Korea Challenger Match | bdd, fury, pilot, Lehends, Shiphter","video_date":"2015-11-01T11:10:03.627+09:00","view_ct":15,"id":"5636b7eb6e6577298c000004"},{"play_time":"4:26","thumbnail":"http://i.ytimg.com/vi/JtYNg8-nPjA/mqdefault.jpg","title":"EDG Deft - Tristana vs Kalista - KR LOL SoloQ Highlights","video_date":"2015-11-01T15:10:04.667+09:00","view_ct":13,"id":"5636b7ec6e6577298c00000f"}]